luvdis/__init__.py
luvdis/__main__.py
luvdis/analyze.py
luvdis/assemble.py
luvdis/charmap.py
luvdis/common.py
luvdis/config.py
luvdis/disasm.py
luvdis/functions.inc
luvdis/gba-db.pickle
luvdis/rom.py
luvdis/test/__init__.py
luvdis/test/test.py
Luvdis-0.8.0.dist-info/LICENSE
Luvdis-0.8.0.dist-info/METADATA
Luvdis-0.8.0.dist-info/WHEEL
Luvdis-0.8.0.dist-info/entry_points.txt
Luvdis-0.8.0.dist-info/top_level.txt
Luvdis-0.8.0.dist-info/RECORD
