Metadata-Version: 2.1
Name: Luvdis
Version: 0.8.0
Summary: Pure-Python Game Boy Advance Disassembler
Home-page: https://github.com/arantonitis/luvdis
Author: Ariel Antonitis
Author-email: arant@mit.edu
License: MIT
Platform: UNKNOWN
Classifier: Development Status :: 4 - Beta
Classifier: Environment :: Console
Classifier: Topic :: Software Development :: Disassemblers
Classifier: Topic :: System :: Hardware
Classifier: Programming Language :: Python :: 3.6
Classifier: Programming Language :: Python :: 3.7
Classifier: Programming Language :: Python :: 3.8
Requires-Python: >=3.6
Requires-Dist: click (>=7.0)
Requires-Dist: click-default-group
Requires-Dist: tqdm (>=4.0.0)
